[
  {
    "slug": "study_next_js",
    "title": "折腾一番Nextjs",
    "tags": [
      "学习",
      "Nextjs",
      "antd",
      "tailwindcss"
    ],
    "date": "2026-01-29T11:41",
    "summary": "记录一下Nextjs折腾我的过程",
    "cover": "/blogs/study_next_js/161476c29bcf1704.jpg",
    "hidden": false,
    "category": "学习"
  },
  {
    "slug": "taro_weapp_h5",
    "title": "用Taro写一个静态小程序+H5",
    "tags": [
      "taro"
    ],
    "date": "2026-01-04T15:54",
    "summary": "一个简易需求，需要写一个静态页面，同时支持h5和小程序，使用taro就是很自然的事情了",
    "cover": "/blogs/taro_weapp_h5/498f978fb0a6cde5.jpg",
    "hidden": false,
    "category": "日常"
  },
  {
    "slug": "pywebview-rapidocr",
    "title": "PyWebview+rapidocr打包记录",
    "tags": [
      "python",
      "webview",
      "ocr"
    ],
    "date": "2025-12-22T17:15",
    "summary": "心血来潮想要写一个OCR桌面应用，记录一下曲折的打包经历",
    "cover": "/blogs/pywebview-rapidocr/34692f0342b1da6d.png",
    "hidden": false,
    "category": "学习"
  },
  {
    "slug": "about-remote-desktop",
    "title": "关于远程桌面",
    "tags": [
      "日常",
      "window"
    ],
    "date": "2025-12-16",
    "summary": "关于快捷修改window多显示器展示方式",
    "cover": "/blogs/about-remote-desktop/61c52edd1a48aa21.png"
  },
  {
    "slug": "to-flutter",
    "title": "探索一番Flutter",
    "tags": [
      "Flutter"
    ],
    "date": "2025-12-09T08:00",
    "summary": "之前用react native写了一个安卓应用，想要加一些渐变阴影太麻烦了，试一试Flutter如何",
    "cover": "/blogs/to-flutter/240afa8bf174729e.jpg",
    "hidden": false,
    "category": ""
  },
  {
    "slug": "javascript-base",
    "title": "JavaScript教程阅读笔记（更新中）",
    "tags": [],
    "date": "2025-12-08",
    "summary": "",
    "cover": "/blogs/javascript-base/ad0b95262479506f.jpg"
  },
  {
    "slug": "about-blog",
    "title": "关于博客",
    "tags": [],
    "date": "2025-12-03",
    "summary": "关于博客的一系列折腾",
    "cover": "/blogs/about-blog/55a3a4f38cad1f50.jpg"
  },
  {
    "slug": "readme",
    "title": "博客模板",
    "tags": [
      "开源"
    ],
    "date": "2025-11-16T08:00",
    "summary": "2025-blog-public 项目的使用说明以及注意事项",
    "cover": "/blogs/readme/9532a65cc32ca5eb.png"
  }
]